pytest_bdd_html/__init__.py
pytest_bdd_html/plugin.py
pytest_bdd_html/resources/style.css
pytest_bdd_html-0.1.14a0.dist-info/LICENSE
pytest_bdd_html-0.1.14a0.dist-info/METADATA
pytest_bdd_html-0.1.14a0.dist-info/WHEEL
pytest_bdd_html-0.1.14a0.dist-info/entry_points.txt
pytest_bdd_html-0.1.14a0.dist-info/top_level.txt
pytest_bdd_html-0.1.14a0.dist-info/RECORD
