Metadata-Version: 2.1
Name: pytest-bdd-html
Version: 0.1.14a0
Summary: pytest plugin to display BDD info in HTML test report
Author-email: slavos1 <slavos1@example.com>
License: MIT
Project-URL: Homepage, https://github.com/slavos1/pytest-bdd-html
Project-URL: Documentation, https://github.com/slavos1/pytest-bdd-html/blob/main/README.rst
Keywords: pytest,html,bdd,report
Classifier: Development Status :: 3 - Alpha
Classifier: Framework :: Pytest
Classifier: Intended Audience :: Developers
Classifier: License :: OSI Approved :: MIT License
Classifier: Topic :: Software Development :: Quality Assurance
Classifier: Topic :: Software Development :: Testing
Classifier: Topic :: Utilities
Classifier: Programming Language :: Python
Classifier: Programming Language :: Python :: 3
Classifier: Programming Language :: Python :: 3.7
Classifier: Programming Language :: Python :: 3.8
Classifier: Programming Language :: Python :: 3.9
Classifier: Programming Language :: Python :: 3 :: Only
Requires-Python: >=3.7
License-File: LICENSE
Requires-Dist: pytest (!=6.0.0,>=5.0)
Requires-Dist: pytest-metadata
Requires-Dist: pytest-bdd
Requires-Dist: pytest-html
